helpme_py.cpython-314-x86_64-linux-gnu.so
helpme_py.libs/libblas-fe34f726.so.3.8.0
helpme_py.libs/libfftw3-6b983104.so.3.5.5
helpme_py.libs/libfftw3f-b4465a35.so.3.5.5
helpme_py.libs/libfftw3l-cef73d68.so.3.5.5
helpme_py.libs/libgfortran-8f1e9814.so.5.0.0
helpme_py.libs/libgomp-870cb1d0.so.1.0.0
helpme_py.libs/libquadmath-828275a7.so.0.0.0
helpme_py-0.2.2.dist-info/METADATA
helpme_py-0.2.2.dist-info/WHEEL
helpme_py-0.2.2.dist-info/RECORD
helpme_py-0.2.2.dist-info/licenses/LICENSE
