Metadata-Version: 2.2
Name: helpme_py
Version: 0.2.2
Summary: helPME-py: A Python Utility for Particle Mesh Ewald based on helPME
License: BSD 3-Clause License
Requires-Python: >=3.10
Requires-Dist: numpy>1.23.0
Provides-Extra: docs
Requires-Dist: sphinx; extra == "docs"
Requires-Dist: breathe; extra == "docs"
Requires-Dist: exhale; extra == "docs"
Requires-Dist: doxygen; extra == "docs"
Requires-Dist: furo; extra == "docs"
Provides-Extra: docs-pdf
Requires-Dist: latex; extra == "docs-pdf"
